{"type":"FeatureCollection","features":[{"type":"Feature","id":1,"geometry":{"type":"Point","coordinates":[13.073084499663695,47.782051493713944]},"properties":{"OBJECTID":1,"Address":"Egger-Lienzgasse 3","Info":"Unser Studentenheim \"Haus Paracelsus\" befindet sich in naturnaher Lage am botanischen Garten gegenüber der Naturwissenschaftlichen Fakultät und ist nur eine Busstation vom UNIPARK Nonntal und der Salzburger Altstadt entfernt.","Link":"https://www.wist-salzburg.com/de/haus-paracelsus","name":"Haus Humboldt"}},{"type":"Feature","id":1,"geometry":{"type":"Point","coordinates":[13.046996645871811,47.811814972098]},"properties":{"OBJECTID":2,"Address":"Merianstraße 40","Info":"Unser Studentenheim \"Haus Merian\" befindet sich im Zentrum der Stadt direkt am Salzburger Hauptbahnhof. Es bestehen beste öffentliche Verkehrsanbindungen zur FH-Salzburg, Science City Itzling und der Salzburger Altstadt.","Link":"https://www.wist-salzburg.com/de/haus-merian","name":"Studentenheim Merian"}},{"type":"Feature","id":7,"geometry":{"type":"Point","coordinates":[13.061559899696004,47.78730689281172]},"properties":{"OBJECTID":3,"Address":"Konrad Laib Straße 10","Info":"Unser Studentenheim \"Haus Humboldt\" befindet sich in naturnaher Lage im Süden Salzburgs und ist nur wenige Busstationen von der Naturwissenschaftlichen Fakultät, dem UNIPARK Nonntal und der Salzburger Altstadt entfernt.","Link":"https://www.wist-salzburg.com/de/haus-humboldt","name":"Haus Paracelsus"}}]}